gelviz/__init__.py
gelviz/basic.py
gelviz-0.9.dist-info/LICENSE
gelviz-0.9.dist-info/METADATA
gelviz-0.9.dist-info/WHEEL
gelviz-0.9.dist-info/top_level.txt
gelviz-0.9.dist-info/RECORD
