Metadata-Version: 2.1
Name: gelviz
Version: 0.9
Summary: A python package for plotting genomic elements in a genome browser style
Home-page: https://gelviz.readthedocs.io/en/latest
Author: Matthias Bieg
Author-email: matthias.bieg@gmail.com
License: UNKNOWN
Platform: UNKNOWN
Classifier: Programming Language :: Python :: 3
Classifier: License :: OSI Approved :: BSD License
Classifier: Operating System :: OS Independent
Requires-Python: >=3.0
